setup.py
pg_table_markdown/__init__.py
pg_table_markdown/database.py
pg_table_markdown/queries.py
pg_table_markdown/utils.py
pg_table_markdown.egg-info/PKG-INFO
pg_table_markdown.egg-info/SOURCES.txt
pg_table_markdown.egg-info/dependency_links.txt
pg_table_markdown.egg-info/entry_points.txt
pg_table_markdown.egg-info/requires.txt
pg_table_markdown.egg-info/top_level.txt