Metadata-Version: 1.0
Name: pg-table-markdown
Version: 1.0.4
Summary: A command line tool that generates markdown documentation for Postgres tables in a given schema
Home-page: https://github.com/vokal/pg-table-markdown
Author: Vokal
Author-email: pypi@vokal.io
License: UNKNOWN
Platform: UNKNOWN
